digital_experiments/__init__.py
digital_experiments/backends.py
digital_experiments/callbacks.py
digital_experiments/controllers.py
digital_experiments/core.py
digital_experiments/experiment.py
digital_experiments/util.py
digital_experiments-2.0.4.dist-info/LICENSE
digital_experiments-2.0.4.dist-info/METADATA
digital_experiments-2.0.4.dist-info/WHEEL
digital_experiments-2.0.4.dist-info/top_level.txt
digital_experiments-2.0.4.dist-info/RECORD
