Metadata-Version: 2.1
Name: digital-experiments
Version: 2.0.4
Summary: Keep track of digital experiments.
Author-email: John Gardner <gardner.john97@gmail.com>
License: Copyright 2022 John Gardner
Project-URL: Homepage, https://github.com/jla-gardner/digital-experiments
Keywords: config,experiments,optimisation
Classifier: License :: OSI Approved :: MIT License
Classifier: Programming Language :: Python
Classifier: Programming Language :: Python :: 3
Requires-Python: >=3.8
License-File: LICENSE
Requires-Dist: pyyaml
Provides-Extra: dev
Requires-Dist: notebook ; extra == 'dev'
Requires-Dist: ruff ; extra == 'dev'
Requires-Dist: bumpver ; extra == 'dev'
Requires-Dist: sphinx ; extra == 'dev'
Requires-Dist: furo ; extra == 'dev'
Requires-Dist: nbsphinx ; extra == 'dev'
Requires-Dist: sphinx-autobuild ; extra == 'dev'
Requires-Dist: sphinxext-opengraph ; extra == 'dev'
Requires-Dist: sphinx-copybutton ; extra == 'dev'
Requires-Dist: sphinx-design ; extra == 'dev'
Requires-Dist: sphinx-codeautolink ; extra == 'dev'
Requires-Dist: pandas ; extra == 'dev'
Provides-Extra: publish
Requires-Dist: build ; extra == 'publish'
Requires-Dist: twine ; extra == 'publish'
Provides-Extra: test
Requires-Dist: pytest ; extra == 'test'
Requires-Dist: pytest-cov ; extra == 'test'
Requires-Dist: pandas ; extra == 'test'
